jupyterlab_iframe/__init__.py
jupyterlab_iframe/_version.py
jupyterlab_iframe/extension.py
jupyterlab_iframe/proxy.py
jupyterlab_iframe/extension/jupyterlab_iframe.json
jupyterlab_iframe/labextension/package.json
jupyterlab_iframe/labextension/static/568.792154b58b90c0bc4d48.js
jupyterlab_iframe/labextension/static/873.9c195a127211ef0c49f3.js
jupyterlab_iframe/labextension/static/remoteEntry.d8f5f45433a49939456d.js
jupyterlab_iframe/labextension/static/style.js
jupyterlab_iframe/labextension/static/third-party-licenses.json
jupyterlab_iframe/tests/__init__.py
jupyterlab_iframe/tests/test_all.py
jupyterlab_iframe/tests/test_extension.py
jupyterlab_iframe/tests/test_init.py
jupyterlab_iframe-0.5.0.data/data/etc/jupyter/jupyter_server_config.d/jupyterlab_iframe.json
jupyterlab_iframe-0.5.0.data/data/share/jupyter/labextensions/jupyterlab_iframe/package.json
jupyterlab_iframe-0.5.0.data/data/share/jupyter/labextensions/jupyterlab_iframe/static/568.792154b58b90c0bc4d48.js
jupyterlab_iframe-0.5.0.data/data/share/jupyter/labextensions/jupyterlab_iframe/static/873.9c195a127211ef0c49f3.js
jupyterlab_iframe-0.5.0.data/data/share/jupyter/labextensions/jupyterlab_iframe/static/remoteEntry.d8f5f45433a49939456d.js
jupyterlab_iframe-0.5.0.data/data/share/jupyter/labextensions/jupyterlab_iframe/static/style.js
jupyterlab_iframe-0.5.0.data/data/share/jupyter/labextensions/jupyterlab_iframe/static/third-party-licenses.json
jupyterlab_iframe-0.5.0.dist-info/METADATA
jupyterlab_iframe-0.5.0.dist-info/WHEEL
jupyterlab_iframe-0.5.0.dist-info/licenses/LICENSE
jupyterlab_iframe-0.5.0.dist-info/RECORD
