Metadata-Version: 2.1
Name: jupyterlab_iframe
Version: 0.5.0
Summary: IFrame widgets for JupyterLab
Project-URL: Repository, https://github.com/timkpaine/jupyterlab_iframe
Project-URL: Homepage, https://github.com/timkpaine/jupyterlab_iframe
Author: Tim Paine
License:                                  Apache License
License-File: LICENSE
Keywords: Jupyter,JupyterLab
Classifier: Development Status :: 4 - Beta
Classifier: Framework :: Jupyter
Classifier: Framework :: Jupyter :: JupyterLab
Classifier: License :: OSI Approved :: Apache Software License
Classifier: Programming Language :: Python
Classifier: Programming Language :: Python :: 3
Classifier: Programming Language :: Python :: 3.7
Classifier: Programming Language :: Python :: 3.8
Classifier: Programming Language :: Python :: 3.9
Classifier: Programming Language :: Python :: 3.10
Classifier: Programming Language :: Python :: 3.11
Requires-Python: >=3.7
Requires-Dist: jupyterlab<5,>=4
Requires-Dist: requests>=2.22.0
Requires-Dist: tornado-proxy-handlers>=0.0.4
Provides-Extra: develop
Requires-Dist: black>=23; extra == 'develop'
Requires-Dist: check-manifest; extra == 'develop'
Requires-Dist: pytest; extra == 'develop'
Requires-Dist: pytest-cov; extra == 'develop'
Requires-Dist: ruff; extra == 'develop'
Provides-Extra: test
Requires-Dist: pytest; extra == 'test'
Requires-Dist: pytest-cov; extra == 'test'
